Classfile jar:file://{tempDir}/target/calls.jar!/calls/CallsSample$Root.class
  Last modified 27 Oct 2023; size 635 bytes
  SHA-256 checksum 05db19678c79a8715bbc3cafc8f5ce7b0909973d569a96f79aea389109a06fb3
  Compiled from "CallsSample.java"
public class calls.CallsSample$Root
  minor version: 0
  major version: 61
  flags: (0x0021) ACC_PUBLIC, ACC_SUPER
  this_class: #17                         // calls/CallsSample$Root
  super_class: #2                         // java/lang/Object
  interfaces: 0, fields: 0, methods: 3, attributes: 3
Constant pool:
   #1 = Methodref          #2.#3          // java/lang/Object."<init>":()V
   #2 = Class              #4             // java/lang/Object
   #3 = NameAndType        #5:#6          // "<init>":()V
   #4 = Utf8               java/lang/Object
   #5 = Utf8               <init>
   #6 = Utf8               ()V
   #7 = String             #8             // Base#meth1()
   #8 = Utf8               Base#meth1()
   #9 = InterfaceMethodref #10.#11        // java/util/function/Consumer.accept:(Ljava/lang/Object;)V
  #10 = Class              #12            // java/util/function/Consumer
  #11 = NameAndType        #13:#14        // accept:(Ljava/lang/Object;)V
  #12 = Utf8               java/util/function/Consumer
  #13 = Utf8               accept
  #14 = Utf8               (Ljava/lang/Object;)V
  #15 = String             #16            // Base#meth2()
  #16 = Utf8               Base#meth2()
  #17 = Class              #18            // calls/CallsSample$Root
  #18 = Utf8               calls/CallsSample$Root
  #19 = Utf8               Code
  #20 = Utf8               LineNumberTable
  #21 = Utf8               meth1
  #22 = Utf8               (Ljava/util/function/Consumer;)V
  #23 = Utf8               Signature
  #24 = Utf8               (Ljava/util/function/Consumer<Ljava/lang/String;>;)V
  #25 = Utf8               meth2
  #26 = Utf8               SourceFile
  #27 = Utf8               CallsSample.java
  #28 = Utf8               NestHost
  #29 = Class              #30            // calls/CallsSample
  #30 = Utf8               calls/CallsSample
  #31 = Utf8               InnerClasses
  #32 = Utf8               Root
{
  public calls.CallsSample$Root();
    descriptor: ()V
    flags: (0x0001) ACC_PUBLIC
    Code:
      stack=1, locals=1, args_size=1
         0: aload_0
         1: invokespecial #1                  // Method java/lang/Object."<init>":()V
         4: return
      LineNumberTable:
        line 7: 0

  void meth1(java.util.function.Consumer<java.lang.String>);
    descriptor: (Ljava/util/function/Consumer;)V
    flags: (0x0000)
    Code:
      stack=2, locals=2, args_size=2
         0: aload_1
         1: ldc           #7                  // String Base#meth1()
         3: invokeinterface #9,  2            // InterfaceMethod java/util/function/Consumer.accept:(Ljava/lang/Object;)V
         8: return
      LineNumberTable:
        line 9: 0
        line 10: 8
    Signature: #24                          // (Ljava/util/function/Consumer<Ljava/lang/String;>;)V

  void meth2(java.util.function.Consumer<java.lang.String>);
    descriptor: (Ljava/util/function/Consumer;)V
    flags: (0x0000)
    Code:
      stack=2, locals=2, args_size=2
         0: aload_1
         1: ldc           #15                 // String Base#meth2()
         3: invokeinterface #9,  2            // InterfaceMethod java/util/function/Consumer.accept:(Ljava/lang/Object;)V
         8: return
      LineNumberTable:
        line 13: 0
        line 14: 8
    Signature: #24                          // (Ljava/util/function/Consumer<Ljava/lang/String;>;)V
}
SourceFile: "CallsSample.java"
NestHost: class calls/CallsSample
InnerClasses:
  public static #32= #17 of #29;          // Root=class calls/CallsSample$Root of class calls/CallsSample
Classfile jar:file://{tempDir}/target/calls.jar!/calls/CallsSample.class
  Last modified 27 Oct 2023; size 382 bytes
  SHA-256 checksum a61fc06428027373093f80c6bf9f38fa366efe1ac07a8aeb5b5ffb50dda8cb95
  Compiled from "CallsSample.java"
public class calls.CallsSample
  minor version: 0
  major version: 61
  flags: (0x0021) ACC_PUBLIC, ACC_SUPER
  this_class: #7                          // calls/CallsSample
  super_class: #2                         // java/lang/Object
  interfaces: 0, fields: 0, methods: 1, attributes: 3
Constant pool:
   #1 = Methodref          #2.#3          // java/lang/Object."<init>":()V
   #2 = Class              #4             // java/lang/Object
   #3 = NameAndType        #5:#6          // "<init>":()V
   #4 = Utf8               java/lang/Object
   #5 = Utf8               <init>
   #6 = Utf8               ()V
   #7 = Class              #8             // calls/CallsSample
   #8 = Utf8               calls/CallsSample
   #9 = Utf8               Code
  #10 = Utf8               LineNumberTable
  #11 = Utf8               SourceFile
  #12 = Utf8               CallsSample.java
  #13 = Utf8               NestMembers
  #14 = Class              #15            // calls/CallsSample$Main
  #15 = Utf8               calls/CallsSample$Main
  #16 = Class              #17            // calls/CallsSample$SubA
  #17 = Utf8               calls/CallsSample$SubA
  #18 = Class              #19            // calls/CallsSample$Root
  #19 = Utf8               calls/CallsSample$Root
  #20 = Utf8               InnerClasses
  #21 = Utf8               Main
  #22 = Utf8               SubA
  #23 = Utf8               Root
{
  public calls.CallsSample();
    descriptor: ()V
    flags: (0x0001) ACC_PUBLIC
    Code:
      stack=1, locals=1, args_size=1
         0: aload_0
         1: invokespecial #1                  // Method java/lang/Object."<init>":()V
         4: return
      LineNumberTable:
        line 5: 0
}
SourceFile: "CallsSample.java"
NestMembers:
  calls/CallsSample$Main
  calls/CallsSample$SubA
  calls/CallsSample$Root
InnerClasses:
  public static #21= #14 of #7;           // Main=class calls/CallsSample$Main of class calls/CallsSample
  public static #22= #16 of #7;           // SubA=class calls/CallsSample$SubA of class calls/CallsSample
  public static #23= #18 of #7;           // Root=class calls/CallsSample$Root of class calls/CallsSample
Classfile jar:file://{tempDir}/target/calls.jar!/calls/CallsSample$Main.class
  Last modified 27 Oct 2023; size 888 bytes
  SHA-256 checksum 9ff6e963383f41a0b7d47e7e2b7e949886a412d1ab09d264da56017a2995c6cf
  Compiled from "CallsSample.java"
public class calls.CallsSample$Main
  minor version: 0
  major version: 61
  flags: (0x0021) ACC_PUBLIC, ACC_SUPER
  this_class: #20                         // calls/CallsSample$Main
  super_class: #2                         // java/lang/Object
  interfaces: 0, fields: 0, methods: 3, attributes: 3
Constant pool:
   #1 = Methodref          #2.#3          // java/lang/Object."<init>":()V
   #2 = Class              #4             // java/lang/Object
   #3 = NameAndType        #5:#6          // "<init>":()V
   #4 = Utf8               java/lang/Object
   #5 = Utf8               <init>
   #6 = Utf8               ()V
   #7 = Methodref          #8.#9          // calls/CallsSample$SubA.meth1:(Ljava/util/function/Consumer;)V
   #8 = Class              #10            // calls/CallsSample$SubA
   #9 = NameAndType        #11:#12        // meth1:(Ljava/util/function/Consumer;)V
  #10 = Utf8               calls/CallsSample$SubA
  #11 = Utf8               meth1
  #12 = Utf8               (Ljava/util/function/Consumer;)V
  #13 = Methodref          #8.#14         // calls/CallsSample$SubA.meth2:(Ljava/util/function/Consumer;)V
  #14 = NameAndType        #15:#12        // meth2:(Ljava/util/function/Consumer;)V
  #15 = Utf8               meth2
  #16 = Methodref          #17.#9         // calls/CallsSample$Root.meth1:(Ljava/util/function/Consumer;)V
  #17 = Class              #18            // calls/CallsSample$Root
  #18 = Utf8               calls/CallsSample$Root
  #19 = Methodref          #17.#14        // calls/CallsSample$Root.meth2:(Ljava/util/function/Consumer;)V
  #20 = Class              #21            // calls/CallsSample$Main
  #21 = Utf8               calls/CallsSample$Main
  #22 = Utf8               Code
  #23 = Utf8               LineNumberTable
  #24 = Utf8               meth3
  #25 = Utf8               (Lcalls/CallsSample$SubA;Ljava/util/function/Consumer;)V
  #26 = Utf8               Signature
  #27 = Utf8               (Lcalls/CallsSample$SubA;Ljava/util/function/Consumer<Ljava/lang/String;>;)V
  #28 = Utf8               meth4
  #29 = Utf8               (Lcalls/CallsSample$Root;Ljava/util/function/Consumer;)V
  #30 = Utf8               (Lcalls/CallsSample$Root;Ljava/util/function/Consumer<Ljava/lang/String;>;)V
  #31 = Utf8               SourceFile
  #32 = Utf8               CallsSample.java
  #33 = Utf8               NestHost
  #34 = Class              #35            // calls/CallsSample
  #35 = Utf8               calls/CallsSample
  #36 = Utf8               InnerClasses
  #37 = Utf8               SubA
  #38 = Utf8               Root
  #39 = Utf8               Main
{
  public calls.CallsSample$Main();
    descriptor: ()V
    flags: (0x0001) ACC_PUBLIC
    Code:
      stack=1, locals=1, args_size=1
         0: aload_0
         1: invokespecial #1                  // Method java/lang/Object."<init>":()V
         4: return
      LineNumberTable:
        line 33: 0

  void meth3(calls.CallsSample$SubA, java.util.function.Consumer<java.lang.String>);
    descriptor: (Lcalls/CallsSample$SubA;Ljava/util/function/Consumer;)V
    flags: (0x0000)
    Code:
      stack=2, locals=3, args_size=3
         0: aload_1
         1: aload_2
         2: invokevirtual #7                  // Method calls/CallsSample$SubA.meth1:(Ljava/util/function/Consumer;)V
         5: aload_1
         6: aload_2
         7: invokevirtual #13                 // Method calls/CallsSample$SubA.meth2:(Ljava/util/function/Consumer;)V
        10: return
      LineNumberTable:
        line 35: 0
        line 36: 5
        line 37: 10
    Signature: #27                          // (Lcalls/CallsSample$SubA;Ljava/util/function/Consumer<Ljava/lang/String;>;)V

  void meth4(calls.CallsSample$Root, java.util.function.Consumer<java.lang.String>);
    descriptor: (Lcalls/CallsSample$Root;Ljava/util/function/Consumer;)V
    flags: (0x0000)
    Code:
      stack=2, locals=3, args_size=3
         0: aload_1
         1: aload_2
         2: invokevirtual #16                 // Method calls/CallsSample$Root.meth1:(Ljava/util/function/Consumer;)V
         5: aload_1
         6: aload_2
         7: invokevirtual #19                 // Method calls/CallsSample$Root.meth2:(Ljava/util/function/Consumer;)V
        10: return
      LineNumberTable:
        line 40: 0
        line 41: 5
        line 42: 10
    Signature: #30                          // (Lcalls/CallsSample$Root;Ljava/util/function/Consumer<Ljava/lang/String;>;)V
}
SourceFile: "CallsSample.java"
NestHost: class calls/CallsSample
InnerClasses:
  public static #37= #8 of #34;           // SubA=class calls/CallsSample$SubA of class calls/CallsSample
  public static #38= #17 of #34;          // Root=class calls/CallsSample$Root of class calls/CallsSample
  public static #39= #20 of #34;          // Main=class calls/CallsSample$Main of class calls/CallsSample
Classfile jar:file://{tempDir}/target/calls.jar!/calls/CallsSample$SubA.class
  Last modified 27 Oct 2023; size 1031 bytes
  SHA-256 checksum 83c87cd96f21b9a62dc7f7cede19cd26143f7ac06a1defd98c26ae92a7975e1c
  Compiled from "CallsSample.java"
public class calls.CallsSample$SubA extends calls.CallsSample$Root
  minor version: 0
  major version: 61
  flags: (0x0021) ACC_PUBLIC, ACC_SUPER
  this_class: #16                         // calls/CallsSample$SubA
  super_class: #2                         // calls/CallsSample$Root
  interfaces: 0, fields: 0, methods: 4, attributes: 3
Constant pool:
   #1 = Methodref          #2.#3          // calls/CallsSample$Root."<init>":()V
   #2 = Class              #4             // calls/CallsSample$Root
   #3 = NameAndType        #5:#6          // "<init>":()V
   #4 = Utf8               calls/CallsSample$Root
   #5 = Utf8               <init>
   #6 = Utf8               ()V
   #7 = String             #8             // SubA#meth1()
   #8 = Utf8               SubA#meth1()
   #9 = InterfaceMethodref #10.#11        // java/util/function/Consumer.accept:(Ljava/lang/Object;)V
  #10 = Class              #12            // java/util/function/Consumer
  #11 = NameAndType        #13:#14        // accept:(Ljava/lang/Object;)V
  #12 = Utf8               java/util/function/Consumer
  #13 = Utf8               accept
  #14 = Utf8               (Ljava/lang/Object;)V
  #15 = Methodref          #16.#17        // calls/CallsSample$SubA.meth1:(Ljava/util/function/Consumer;)V
  #16 = Class              #18            // calls/CallsSample$SubA
  #17 = NameAndType        #19:#20        // meth1:(Ljava/util/function/Consumer;)V
  #18 = Utf8               calls/CallsSample$SubA
  #19 = Utf8               meth1
  #20 = Utf8               (Ljava/util/function/Consumer;)V
  #21 = Methodref          #16.#22        // calls/CallsSample$SubA.meth2:(Ljava/util/function/Consumer;)V
  #22 = NameAndType        #23:#20        // meth2:(Ljava/util/function/Consumer;)V
  #23 = Utf8               meth2
  #24 = Methodref          #2.#17         // calls/CallsSample$Root.meth1:(Ljava/util/function/Consumer;)V
  #25 = Methodref          #2.#22         // calls/CallsSample$Root.meth2:(Ljava/util/function/Consumer;)V
  #26 = Utf8               Code
  #27 = Utf8               LineNumberTable
  #28 = Utf8               Signature
  #29 = Utf8               (Ljava/util/function/Consumer<Ljava/lang/String;>;)V
  #30 = Utf8               meth3
  #31 = Utf8               (Lcalls/CallsSample$SubA;Ljava/util/function/Consumer;)V
  #32 = Utf8               (Lcalls/CallsSample$SubA;Ljava/util/function/Consumer<Ljava/lang/String;>;)V
  #33 = Utf8               meth4
  #34 = Utf8               (Lcalls/CallsSample$Root;Ljava/util/function/Consumer;)V
  #35 = Utf8               (Lcalls/CallsSample$Root;Ljava/util/function/Consumer<Ljava/lang/String;>;)V
  #36 = Utf8               SourceFile
  #37 = Utf8               CallsSample.java
  #38 = Utf8               NestHost
  #39 = Class              #40            // calls/CallsSample
  #40 = Utf8               calls/CallsSample
  #41 = Utf8               InnerClasses
  #42 = Utf8               Root
  #43 = Utf8               SubA
{
  public calls.CallsSample$SubA();
    descriptor: ()V
    flags: (0x0001) ACC_PUBLIC
    Code:
      stack=1, locals=1, args_size=1
         0: aload_0
         1: invokespecial #1                  // Method calls/CallsSample$Root."<init>":()V
         4: return
      LineNumberTable:
        line 17: 0

  void meth1(java.util.function.Consumer<java.lang.String>);
    descriptor: (Ljava/util/function/Consumer;)V
    flags: (0x0000)
    Code:
      stack=2, locals=2, args_size=2
         0: aload_1
         1: ldc           #7                  // String SubA#meth1()
         3: invokeinterface #9,  2            // InterfaceMethod java/util/function/Consumer.accept:(Ljava/lang/Object;)V
         8: return
      LineNumberTable:
        line 19: 0
        line 20: 8
    Signature: #29                          // (Ljava/util/function/Consumer<Ljava/lang/String;>;)V

  void meth3(calls.CallsSample$SubA, java.util.function.Consumer<java.lang.String>);
    descriptor: (Lcalls/CallsSample$SubA;Ljava/util/function/Consumer;)V
    flags: (0x0000)
    Code:
      stack=2, locals=3, args_size=3
         0: aload_1
         1: aload_2
         2: invokevirtual #15                 // Method meth1:(Ljava/util/function/Consumer;)V
         5: aload_1
         6: aload_2
         7: invokevirtual #21                 // Method meth2:(Ljava/util/function/Consumer;)V
        10: return
      LineNumberTable:
        line 23: 0
        line 24: 5
        line 25: 10
    Signature: #32                          // (Lcalls/CallsSample$SubA;Ljava/util/function/Consumer<Ljava/lang/String;>;)V

  void meth4(calls.CallsSample$Root, java.util.function.Consumer<java.lang.String>);
    descriptor: (Lcalls/CallsSample$Root;Ljava/util/function/Consumer;)V
    flags: (0x0000)
    Code:
      stack=2, locals=3, args_size=3
         0: aload_1
         1: aload_2
         2: invokevirtual #24                 // Method calls/CallsSample$Root.meth1:(Ljava/util/function/Consumer;)V
         5: aload_1
         6: aload_2
         7: invokevirtual #25                 // Method calls/CallsSample$Root.meth2:(Ljava/util/function/Consumer;)V
        10: return
      LineNumberTable:
        line 28: 0
        line 29: 5
        line 30: 10
    Signature: #35                          // (Lcalls/CallsSample$Root;Ljava/util/function/Consumer<Ljava/lang/String;>;)V
}
SourceFile: "CallsSample.java"
NestHost: class calls/CallsSample
InnerClasses:
  public static #42= #2 of #39;           // Root=class calls/CallsSample$Root of class calls/CallsSample
  public static #43= #16 of #39;          // SubA=class calls/CallsSample$SubA of class calls/CallsSample
